CHANGES.rst
LICENSE
MANIFEST.in
README.rst
setup.py
simplerouter.py
tests.py
tox.ini
docs/changelog.rst
docs/conf.py
docs/index.rst
simplerouter.egg-info/PKG-INFO
simplerouter.egg-info/SOURCES.txt
simplerouter.egg-info/dependency_links.txt
simplerouter.egg-info/requires.txt
simplerouter.egg-info/top_level.txt