Metadata-Version: 1.1
Name: simplerouter
Version: 1.2
Summary: A very simple WebOb based router
Home-page: http://bitbucket.org/rschoon/simplerouter
Author: Robin Schoonover
Author-email: robin@cornhooves.org
License: MIT
Platform: UNKNOWN
Classifier: Development Status :: 5 - Production/Stable
Classifier: Environment :: Web Environment
Classifier: Intended Audience :: Developers
Classifier: License :: OSI Approved :: MIT License
Classifier: Programming Language :: Python :: 3
Classifier: Operating System :: OS Independent
Classifier: Topic :: Internet :: WWW/HTTP :: WSGI
